scrapy_custom_proxy_pool/__init__.py
scrapy_custom_proxy_pool/middlewares.py
scrapy_custom_proxy_pool/policy.py
scrapy_custom_proxy_pool/collector/__init__.py
scrapy_custom_proxy_pool/collector/base.py
scrapy_custom_proxy_pool/collector/qg.py
scrapy_custom_proxy_pool-0.1.0.dist-info/METADATA
scrapy_custom_proxy_pool-0.1.0.dist-info/WHEEL
scrapy_custom_proxy_pool-0.1.0.dist-info/top_level.txt
scrapy_custom_proxy_pool-0.1.0.dist-info/RECORD
