Metadata-Version: 2.1
Name: scrapy-custom-proxy-pool
Version: 0.1.0
Summary: Scrapy proxy pool that allows custom proxy provider
Home-page: https://github.com/acyume/scrapy-custom-proxy-pool
Author: Bohan Chen
Author-email: chacyume@gmail.com
License: MIT
Classifier: Development Status :: 3 - Alpha
Classifier: License :: OSI Approved :: MIT License
Classifier: Intended Audience :: Developers
Classifier: Operating System :: OS Independent
Classifier: Framework :: Scrapy
Classifier: Programming Language :: Python
Classifier: Programming Language :: Python :: 3
Classifier: Programming Language :: Python :: 3.6
Classifier: Programming Language :: Python :: 3.7
Classifier: Programming Language :: Python :: 3.8
Classifier: Programming Language :: Python :: 3.9
Classifier: Programming Language :: Python :: 3.10
Requires-Dist: scrapy
Requires-Dist: requests
